setup.py
slotter/__init__.py
slotter/item.py
slotter/sample.py
slotter/slot.py
slotter/slotter.py
slotter/utils.py
slotter/version.py
slotter.egg-info/PKG-INFO
slotter.egg-info/SOURCES.txt
slotter.egg-info/dependency_links.txt
slotter.egg-info/requires.txt
slotter.egg-info/top_level.txt