Metadata-Version: 1.0
Name: slotter
Version: 0.0.6
Summary: Python library to slot stuff
Home-page: https://github.com/saurabh-hirani/slotter
Author: Saurabh Hirani
Author-email: saurabh.hirani@gmail.com
License: MIT
Platform: UNKNOWN
